{
    "2282": "Twopointzero",
    "UserList": {
        "1": "admin",
        "95534": "usertwo",
        "95543": "userthree",
        "95548": "userfour",
        "95553": "userfive",
        "95558": "usersix",
        "95563": "userseven",
        "100553": "Administrator",
        "101727": "adminv2",
        "102131": "twopointzero",
        "102229": "TestLead"
    },
    "RegionList": {
        "6": "US",
        "10": "UK"
    },
    "AttributeList": {
        "6": [
            6355,
            6334,
            6353,
            6353,
            6354,
            6354,
            6335,
            6336,
            6336,
            6355,
            6336,
            6334,
            6337,
            6334,
            6337,
            6338,
            6337,
            6338,
            6339,
            6338,
            6340,
            6341,
            6339,
            6340,
            6341,
            6340,
            6341,
            6342,
            6342,
            6356,
            6342,
            6356,
            6344,
            6343,
            6344,
            6345,
            6357,
            6344,
            6346,
            6345,
            6346,
            6358,
            6358,
            6347,
            6347,
            6347,
            6348,
            6359,
            6359,
            6348,
            6348,
            6349,
            6360,
            6361,
            6360,
            6350,
            6361,
            6362,
            6363,
            6362,
            6363,
            6364,
            6349,
            6364,
            6351,
            6349,
            6365,
            6366,
            6365,
            6366,
            6375,
            6370,
            6367,
            6352,
            6352,
            6376,
            6368,
            6369,
            6377,
            6378,
            6370,
            6371,
            6372,
            6373,
            6374,
            6352
        ],
        "10": [
            6355,
            6334,
            6353,
            6353,
            6354,
            6354,
            6335,
            6336,
            6355,
            6336,
            6334,
            6336,
            6334,
            6337,
            6337,
            6338,
            6338,
            6337,
            6338,
            6339,
            6340,
            6341,
            6340,
            6339,
            6340,
            6341,
            6342,
            6341,
            6342,
            6342,
            6356,
            6344,
            6356,
            6343,
            6344,
            6357,
            6345,
            6346,
            6344,
            6345,
            6346,
            6358,
            6358,
            6347,
            6347,
            6347,
            6348,
            6359,
            6359,
            6348,
            6348,
            6349,
            6360,
            6361,
            6360,
            6350,
            6361,
            6362,
            6363,
            6362,
            6363,
            6364,
            6349,
            6364,
            6351,
            6349,
            6365,
            6366,
            6365,
            6366,
            6375,
            6370,
            6367,
            6352,
            6352,
            6376,
            6368,
            6369,
            6377,
            6378,
            6370,
            6371,
            6372,
            6373,
            6374,
            6352
        ]
    },
    "AttributeOrder": {
        "6": {
            "6355": {
                "DispalyOrder": "3",
                "ProjectAttributeId": 6355,
                "AttributeName": "Non Core User",
                "AttributeId": 1442,
                "DisplayAttributeName": "Non Core User",
                "ControlName": "TextBox"
            },
            "6334": {
                "DispalyOrder": "5",
                "ProjectAttributeId": 6334,
                "AttributeName": "YPID",
                "AttributeId": 1383,
                "DisplayAttributeName": "YPID",
                "ControlName": "TextBox"
            },
            "6353": {
                "DispalyOrder": "1",
                "ProjectAttributeId": 6353,
                "AttributeName": "Core User",
                "AttributeId": 1440,
                "DisplayAttributeName": "Core User",
                "ControlName": "TextBox",
                "Options": {
                    "core1": "core1",
                    "core2": "core2",
                    "core3": "core3"
                }
            },
            "6354": {
                "DispalyOrder": "2",
                "ProjectAttributeId": 6354,
                "AttributeName": "Agent ID",
                "AttributeId": 1441,
                "DisplayAttributeName": "Agent ID",
                "ControlName": "TextBox"
            },
            "6335": {
                "DispalyOrder": "2",
                "ProjectAttributeId": 6335,
                "AttributeName": "Hoo User",
                "AttributeId": 1432,
                "DisplayAttributeName": "Hoo User",
                "ControlName": "TextBox"
            },
            "6336": {
                "DispalyOrder": "4",
                "ProjectAttributeId": 6336,
                "AttributeName": "Date",
                "AttributeId": 1433,
                "DisplayAttributeName": "Date",
                "ControlName": "TextBox"
            },
            "6337": {
                "DispalyOrder": "6",
                "ProjectAttributeId": 6337,
                "AttributeName": "Tool URL",
                "AttributeId": 1384,
                "DisplayAttributeName": "Tool URL",
                "ControlName": "TextBox"
            },
            "6338": {
                "DispalyOrder": "7",
                "ProjectAttributeId": 6338,
                "AttributeName": "LISTING_NAME",
                "AttributeId": 1385,
                "DisplayAttributeName": "LISTING_NAME",
                "ControlName": "TextBox"
            },
            "6339": {
                "DispalyOrder": "8",
                "ProjectAttributeId": 6339,
                "AttributeName": "URL",
                "AttributeId": 225,
                "DisplayAttributeName": "URL",
                "ControlName": "TextBox"
            },
            "6340": {
                "DispalyOrder": "9",
                "ProjectAttributeId": 6340,
                "AttributeName": "Is the Website for the business?",
                "AttributeId": 1434,
                "DisplayAttributeName": "Is the Website for the business?",
                "ControlName": "DropDownList"
            },
            "6341": {
                "DispalyOrder": "10",
                "ProjectAttributeId": 6341,
                "AttributeName": "Reason",
                "AttributeId": 267,
                "DisplayAttributeName": "Reason",
                "ControlName": "TextBox"
            },
            "6342": {
                "DispalyOrder": "11",
                "ProjectAttributeId": 6342,
                "AttributeName": "NOTES",
                "AttributeId": 263,
                "DisplayAttributeName": "NOTES",
                "ControlName": "TextBox"
            },
            "6356": {
                "DispalyOrder": "12",
                "ProjectAttributeId": 6356,
                "AttributeName": "Is it Closed?",
                "AttributeId": 1443,
                "DisplayAttributeName": "Is it Closed?",
                "ControlName": "DropDownList"
            },
            "6344": {
                "DispalyOrder": "14",
                "ProjectAttributeId": 6344,
                "AttributeName": "Mob_Name",
                "AttributeId": 1389,
                "DisplayAttributeName": "Mob_Name",
                "ControlName": "TextBox"
            },
            "6343": {
                "DispalyOrder": "12",
                "ProjectAttributeId": 6343,
                "AttributeName": "Address Notes",
                "AttributeId": 1435,
                "DisplayAttributeName": "Address Notes",
                "ControlName": "TextBox"
            },
            "6345": {
                "DispalyOrder": "14",
                "ProjectAttributeId": 6345,
                "AttributeName": "Source",
                "AttributeId": 1436,
                "DisplayAttributeName": "Source",
                "ControlName": "TextBox"
            },
            "6357": {
                "DispalyOrder": "13",
                "ProjectAttributeId": 6357,
                "AttributeName": "Input Name",
                "AttributeId": 1388,
                "DisplayAttributeName": "Input Name",
                "ControlName": "TextBox"
            },
            "6346": {
                "DispalyOrder": "15",
                "ProjectAttributeId": 6346,
                "AttributeName": "Remarks",
                "AttributeId": 1437,
                "DisplayAttributeName": "Remarks",
                "ControlName": "TextBox"
            },
            "6358": {
                "DispalyOrder": "15",
                "ProjectAttributeId": 6358,
                "AttributeName": "Input Address",
                "AttributeId": 1392,
                "DisplayAttributeName": "Input Address",
                "ControlName": "TextBox"
            },
            "6347": {
                "DispalyOrder": "16",
                "ProjectAttributeId": 6347,
                "AttributeName": "Mob_Address",
                "AttributeId": 1393,
                "DisplayAttributeName": "Mob_Address",
                "ControlName": "TextBox"
            },
            "6348": {
                "DispalyOrder": "18",
                "ProjectAttributeId": 6348,
                "AttributeName": "Mob_Primary Phone Number",
                "AttributeId": 1397,
                "DisplayAttributeName": "Mob_Primary Phone Number",
                "ControlName": "TextBox"
            },
            "6359": {
                "DispalyOrder": "17",
                "ProjectAttributeId": 6359,
                "AttributeName": "Input Phone",
                "AttributeId": 1396,
                "DisplayAttributeName": "Input Phone",
                "ControlName": "TextBox"
            },
            "6349": {
                "DispalyOrder": "26",
                "ProjectAttributeId": 6349,
                "AttributeName": "Mob_Websites",
                "AttributeId": 1406,
                "DisplayAttributeName": "Mob_Websites",
                "ControlName": "TextBox"
            },
            "6360": {
                "DispalyOrder": "20",
                "ProjectAttributeId": 6360,
                "AttributeName": "Input_Phone numbers",
                "AttributeId": 1399,
                "DisplayAttributeName": "Input_Phone numbers",
                "ControlName": "TextBox"
            },
            "6361": {
                "DispalyOrder": "21",
                "ProjectAttributeId": 6361,
                "AttributeName": "Input_Phone Numbers Type",
                "AttributeId": 1400,
                "DisplayAttributeName": "Input_Phone Numbers Type",
                "ControlName": "TextBox"
            },
            "6350": {
                "DispalyOrder": "20",
                "ProjectAttributeId": 6350,
                "AttributeName": "Hours of Operation",
                "AttributeId": 1427,
                "DisplayAttributeName": "Hours of Operation",
                "ControlName": "TextBox"
            },
            "6362": {
                "DispalyOrder": "22",
                "ProjectAttributeId": 6362,
                "AttributeName": "Mob_Phone numbers",
                "AttributeId": 1401,
                "DisplayAttributeName": "Mob_Phone numbers",
                "ControlName": "TextBox"
            },
            "6363": {
                "DispalyOrder": "23",
                "ProjectAttributeId": 6363,
                "AttributeName": "Mob_Phone Numbers Type",
                "AttributeId": 1402,
                "DisplayAttributeName": "Mob_Phone Numbers Type",
                "ControlName": "TextBox"
            },
            "6364": {
                "DispalyOrder": "25",
                "ProjectAttributeId": 6364,
                "AttributeName": "Input Website",
                "AttributeId": 1405,
                "DisplayAttributeName": "Input Website",
                "ControlName": "TextBox"
            },
            "6351": {
                "DispalyOrder": "25",
                "ProjectAttributeId": 6351,
                "AttributeName": "Additional",
                "AttributeId": 1438,
                "DisplayAttributeName": "Additional",
                "ControlName": "TextBox"
            },
            "6365": {
                "DispalyOrder": "27",
                "ProjectAttributeId": 6365,
                "AttributeName": "Input_Categories_Primary",
                "AttributeId": 1409,
                "DisplayAttributeName": "Input_Categories_Primary",
                "ControlName": "TextBox"
            },
            "6366": {
                "DispalyOrder": "28",
                "ProjectAttributeId": 6366,
                "AttributeName": "Mob_Categories_Primary",
                "AttributeId": 1410,
                "DisplayAttributeName": "Mob_Categories_Primary",
                "ControlName": "TextBox"
            },
            "6375": {
                "DispalyOrder": "28",
                "ProjectAttributeId": 6375,
                "AttributeName": "Comments",
                "AttributeId": 61,
                "DisplayAttributeName": "Comments",
                "ControlName": "MultiTextBox"
            },
            "6370": {
                "DispalyOrder": "34",
                "ProjectAttributeId": 6370,
                "AttributeName": "Mob_Email",
                "AttributeId": 1417,
                "DisplayAttributeName": "Mob_Email",
                "ControlName": "TextBox"
            },
            "6367": {
                "DispalyOrder": "29",
                "ProjectAttributeId": 6367,
                "AttributeName": "Payment_Methods",
                "AttributeId": 1413,
                "DisplayAttributeName": "Payment_Methods",
                "ControlName": "TextBox"
            },
            "6352": {
                "DispalyOrder": "43",
                "ProjectAttributeId": 6352,
                "AttributeName": "Team",
                "AttributeId": 1439,
                "DisplayAttributeName": "Team",
                "ControlName": "TextBox"
            },
            "6376": {
                "DispalyOrder": "31",
                "ProjectAttributeId": 6376,
                "AttributeName": "Batch",
                "AttributeId": 1446,
                "DisplayAttributeName": "Batch",
                "ControlName": "DropDownList",
                "Options": {
                    "batch1": "batch1",
                    "batch2": "batch2"
                }
            },
            "6368": {
                "DispalyOrder": "32",
                "ProjectAttributeId": 6368,
                "AttributeName": "Mob_Payment_Methods",
                "AttributeId": 1414,
                "DisplayAttributeName": "Mob_Payment_Methods",
                "ControlName": "TextBox"
            },
            "6369": {
                "DispalyOrder": "33",
                "ProjectAttributeId": 6369,
                "AttributeName": "Email",
                "AttributeId": 90,
                "DisplayAttributeName": "Email",
                "ControlName": "TextBox"
            },
            "6377": {
                "DispalyOrder": "33",
                "ProjectAttributeId": 6377,
                "AttributeName": "Status",
                "AttributeId": 200,
                "DisplayAttributeName": "Status",
                "ControlName": "TextBox"
            },
            "6378": {
                "DispalyOrder": "34",
                "ProjectAttributeId": 6378,
                "AttributeName": "Input Category",
                "AttributeId": 1447,
                "DisplayAttributeName": "Input Category",
                "ControlName": "DropDownList",
                "Options": {
                    "Automobile": "Automobile",
                    "IT Services": "IT Services"
                }
            },
            "6371": {
                "DispalyOrder": "36",
                "ProjectAttributeId": 6371,
                "AttributeName": "Services & Products",
                "AttributeId": 1444,
                "DisplayAttributeName": "Services & Products",
                "ControlName": "TextBox"
            },
            "6372": {
                "DispalyOrder": "38",
                "ProjectAttributeId": 6372,
                "AttributeName": "Mob_Services & Products",
                "AttributeId": 1445,
                "DisplayAttributeName": "Mob_Services & Products",
                "ControlName": "TextBox"
            },
            "6373": {
                "DispalyOrder": "40",
                "ProjectAttributeId": 6373,
                "AttributeName": "Business Since",
                "AttributeId": 1423,
                "DisplayAttributeName": "Business Since",
                "ControlName": "TextBox"
            },
            "6374": {
                "DispalyOrder": "41",
                "ProjectAttributeId": 6374,
                "AttributeName": "Since",
                "AttributeId": 1424,
                "DisplayAttributeName": "Since",
                "ControlName": "TextBox"
            }
        },
        "10": {
            "6355": {
                "DispalyOrder": "3",
                "ProjectAttributeId": 6355,
                "AttributeName": "Non Core User",
                "AttributeId": 1442,
                "DisplayAttributeName": "Non Core User",
                "ControlName": "TextBox"
            },
            "6334": {
                "DispalyOrder": "5",
                "ProjectAttributeId": 6334,
                "AttributeName": "YPID",
                "AttributeId": 1383,
                "DisplayAttributeName": "YPID",
                "ControlName": "TextBox"
            },
            "6353": {
                "DispalyOrder": "1",
                "ProjectAttributeId": 6353,
                "AttributeName": "Core User",
                "AttributeId": 1440,
                "DisplayAttributeName": "Core User",
                "ControlName": "DropDownList"
            },
            "6354": {
                "DispalyOrder": "2",
                "ProjectAttributeId": 6354,
                "AttributeName": "Agent ID",
                "AttributeId": 1441,
                "DisplayAttributeName": "Agent ID",
                "ControlName": "TextBox"
            },
            "6335": {
                "DispalyOrder": "2",
                "ProjectAttributeId": 6335,
                "AttributeName": "Hoo User",
                "AttributeId": 1432,
                "DisplayAttributeName": "Hoo User",
                "ControlName": "TextBox"
            },
            "6336": {
                "DispalyOrder": "4",
                "ProjectAttributeId": 6336,
                "AttributeName": "Date",
                "AttributeId": 1433,
                "DisplayAttributeName": "Date",
                "ControlName": "TextBox"
            },
            "6337": {
                "DispalyOrder": "6",
                "ProjectAttributeId": 6337,
                "AttributeName": "Tool URL",
                "AttributeId": 1384,
                "DisplayAttributeName": "Tool URL",
                "ControlName": "TextBox"
            },
            "6338": {
                "DispalyOrder": "7",
                "ProjectAttributeId": 6338,
                "AttributeName": "LISTING_NAME",
                "AttributeId": 1385,
                "DisplayAttributeName": "LISTING_NAME",
                "ControlName": "TextBox"
            },
            "6339": {
                "DispalyOrder": "8",
                "ProjectAttributeId": 6339,
                "AttributeName": "URL",
                "AttributeId": 225,
                "DisplayAttributeName": "URL",
                "ControlName": "TextBox"
            },
            "6340": {
                "DispalyOrder": "9",
                "ProjectAttributeId": 6340,
                "AttributeName": "Is the Website for the business?",
                "AttributeId": 1434,
                "DisplayAttributeName": "Is the Website for the business?",
                "ControlName": "DropDownList"
            },
            "6341": {
                "DispalyOrder": "10",
                "ProjectAttributeId": 6341,
                "AttributeName": "Reason",
                "AttributeId": 267,
                "DisplayAttributeName": "Reason",
                "ControlName": "TextBox"
            },
            "6342": {
                "DispalyOrder": "11",
                "ProjectAttributeId": 6342,
                "AttributeName": "NOTES",
                "AttributeId": 263,
                "DisplayAttributeName": "NOTES",
                "ControlName": "TextBox"
            },
            "6356": {
                "DispalyOrder": "12",
                "ProjectAttributeId": 6356,
                "AttributeName": "Is it Closed?",
                "AttributeId": 1443,
                "DisplayAttributeName": "Is it Closed?",
                "ControlName": "DropDownList"
            },
            "6344": {
                "DispalyOrder": "14",
                "ProjectAttributeId": 6344,
                "AttributeName": "Mob_Name",
                "AttributeId": 1389,
                "DisplayAttributeName": "Mob_Name",
                "ControlName": "TextBox"
            },
            "6343": {
                "DispalyOrder": "12",
                "ProjectAttributeId": 6343,
                "AttributeName": "Address Notes",
                "AttributeId": 1435,
                "DisplayAttributeName": "Address Notes",
                "ControlName": "TextBox"
            },
            "6357": {
                "DispalyOrder": "13",
                "ProjectAttributeId": 6357,
                "AttributeName": "Input Name",
                "AttributeId": 1388,
                "DisplayAttributeName": "Input Name",
                "ControlName": "TextBox"
            },
            "6345": {
                "DispalyOrder": "14",
                "ProjectAttributeId": 6345,
                "AttributeName": "Source",
                "AttributeId": 1436,
                "DisplayAttributeName": "Source",
                "ControlName": "TextBox"
            },
            "6346": {
                "DispalyOrder": "15",
                "ProjectAttributeId": 6346,
                "AttributeName": "Remarks",
                "AttributeId": 1437,
                "DisplayAttributeName": "Remarks",
                "ControlName": "TextBox"
            },
            "6358": {
                "DispalyOrder": "15",
                "ProjectAttributeId": 6358,
                "AttributeName": "Input Address",
                "AttributeId": 1392,
                "DisplayAttributeName": "Input Address",
                "ControlName": "TextBox"
            },
            "6347": {
                "DispalyOrder": "16",
                "ProjectAttributeId": 6347,
                "AttributeName": "Mob_Address",
                "AttributeId": 1393,
                "DisplayAttributeName": "Mob_Address",
                "ControlName": "TextBox"
            },
            "6348": {
                "DispalyOrder": "18",
                "ProjectAttributeId": 6348,
                "AttributeName": "Mob_Primary Phone Number",
                "AttributeId": 1397,
                "DisplayAttributeName": "Mob_Primary Phone Number",
                "ControlName": "TextBox"
            },
            "6359": {
                "DispalyOrder": "17",
                "ProjectAttributeId": 6359,
                "AttributeName": "Input Phone",
                "AttributeId": 1396,
                "DisplayAttributeName": "Input Phone",
                "ControlName": "TextBox"
            },
            "6349": {
                "DispalyOrder": "26",
                "ProjectAttributeId": 6349,
                "AttributeName": "Mob_Websites",
                "AttributeId": 1406,
                "DisplayAttributeName": "Mob_Websites",
                "ControlName": "TextBox"
            },
            "6360": {
                "DispalyOrder": "20",
                "ProjectAttributeId": 6360,
                "AttributeName": "Input_Phone numbers",
                "AttributeId": 1399,
                "DisplayAttributeName": "Input_Phone numbers",
                "ControlName": "TextBox"
            },
            "6361": {
                "DispalyOrder": "21",
                "ProjectAttributeId": 6361,
                "AttributeName": "Input_Phone Numbers Type",
                "AttributeId": 1400,
                "DisplayAttributeName": "Input_Phone Numbers Type",
                "ControlName": "TextBox"
            },
            "6350": {
                "DispalyOrder": "20",
                "ProjectAttributeId": 6350,
                "AttributeName": "Hours of Operation",
                "AttributeId": 1427,
                "DisplayAttributeName": "Hours of Operation",
                "ControlName": "TextBox"
            },
            "6362": {
                "DispalyOrder": "22",
                "ProjectAttributeId": 6362,
                "AttributeName": "Mob_Phone numbers",
                "AttributeId": 1401,
                "DisplayAttributeName": "Mob_Phone numbers",
                "ControlName": "TextBox"
            },
            "6363": {
                "DispalyOrder": "23",
                "ProjectAttributeId": 6363,
                "AttributeName": "Mob_Phone Numbers Type",
                "AttributeId": 1402,
                "DisplayAttributeName": "Mob_Phone Numbers Type",
                "ControlName": "TextBox"
            },
            "6364": {
                "DispalyOrder": "25",
                "ProjectAttributeId": 6364,
                "AttributeName": "Input Website",
                "AttributeId": 1405,
                "DisplayAttributeName": "Input Website",
                "ControlName": "TextBox"
            },
            "6351": {
                "DispalyOrder": "25",
                "ProjectAttributeId": 6351,
                "AttributeName": "Additional",
                "AttributeId": 1438,
                "DisplayAttributeName": "Additional",
                "ControlName": "TextBox"
            },
            "6365": {
                "DispalyOrder": "27",
                "ProjectAttributeId": 6365,
                "AttributeName": "Input_Categories_Primary",
                "AttributeId": 1409,
                "DisplayAttributeName": "Input_Categories_Primary",
                "ControlName": "TextBox"
            },
            "6366": {
                "DispalyOrder": "28",
                "ProjectAttributeId": 6366,
                "AttributeName": "Mob_Categories_Primary",
                "AttributeId": 1410,
                "DisplayAttributeName": "Mob_Categories_Primary",
                "ControlName": "TextBox"
            },
            "6375": {
                "DispalyOrder": "28",
                "ProjectAttributeId": 6375,
                "AttributeName": "Comments",
                "AttributeId": 61,
                "DisplayAttributeName": "Comments",
                "ControlName": "MultiTextBox"
            },
            "6370": {
                "DispalyOrder": "34",
                "ProjectAttributeId": 6370,
                "AttributeName": "Mob_Email",
                "AttributeId": 1417,
                "DisplayAttributeName": "Mob_Email",
                "ControlName": "TextBox"
            },
            "6367": {
                "DispalyOrder": "29",
                "ProjectAttributeId": 6367,
                "AttributeName": "Payment_Methods",
                "AttributeId": 1413,
                "DisplayAttributeName": "Payment_Methods",
                "ControlName": "TextBox"
            },
            "6352": {
                "DispalyOrder": "43",
                "ProjectAttributeId": 6352,
                "AttributeName": "Team",
                "AttributeId": 1439,
                "DisplayAttributeName": "Team",
                "ControlName": "TextBox"
            },
            "6376": {
                "DispalyOrder": "31",
                "ProjectAttributeId": 6376,
                "AttributeName": "Batch",
                "AttributeId": 1446,
                "DisplayAttributeName": "Batch",
                "ControlName": "DropDownList"
            },
            "6368": {
                "DispalyOrder": "32",
                "ProjectAttributeId": 6368,
                "AttributeName": "Mob_Payment_Methods",
                "AttributeId": 1414,
                "DisplayAttributeName": "Mob_Payment_Methods",
                "ControlName": "TextBox"
            },
            "6369": {
                "DispalyOrder": "33",
                "ProjectAttributeId": 6369,
                "AttributeName": "Email",
                "AttributeId": 90,
                "DisplayAttributeName": "Email",
                "ControlName": "TextBox"
            },
            "6377": {
                "DispalyOrder": "33",
                "ProjectAttributeId": 6377,
                "AttributeName": "Status",
                "AttributeId": 200,
                "DisplayAttributeName": "Status",
                "ControlName": "TextBox"
            },
            "6378": {
                "DispalyOrder": "34",
                "ProjectAttributeId": 6378,
                "AttributeName": "Input Category",
                "AttributeId": 1447,
                "DisplayAttributeName": "Input Category",
                "ControlName": "DropDownList"
            },
            "6371": {
                "DispalyOrder": "36",
                "ProjectAttributeId": 6371,
                "AttributeName": "Services & Products",
                "AttributeId": 1444,
                "DisplayAttributeName": "Services & Products",
                "ControlName": "TextBox"
            },
            "6372": {
                "DispalyOrder": "38",
                "ProjectAttributeId": 6372,
                "AttributeName": "Mob_Services & Products",
                "AttributeId": 1445,
                "DisplayAttributeName": "Mob_Services & Products",
                "ControlName": "TextBox"
            },
            "6373": {
                "DispalyOrder": "40",
                "ProjectAttributeId": 6373,
                "AttributeName": "Business Since",
                "AttributeId": 1423,
                "DisplayAttributeName": "Business Since",
                "ControlName": "TextBox"
            },
            "6374": {
                "DispalyOrder": "41",
                "ProjectAttributeId": 6374,
                "AttributeName": "Since",
                "AttributeId": 1424,
                "DisplayAttributeName": "Since",
                "ControlName": "TextBox"
            }
        }
    },
    "ModuleAttributes": {
        "6": {
            "1152": {
                "production": {
                    "0": {
                        "AttributeMasterId": 1442,
                        "ProjectAttributeMasterId": 6355,
                        "DispalyOrder": "0",
                        "DisplayAttributeName": "Non Core User",
                        "ControlName": "Label",
                        "AttributeName": "Non Core User"
                    },
                    "1": {
                        "AttributeMasterId": 1440,
                        "ProjectAttributeMasterId": 6353,
                        "DispalyOrder": "1",
                        "DisplayAttributeName": "Core User",
                        "ControlName": "TextBox",
                        "AttributeName": "Core User"
                    },
                    "3": {
                        "AttributeMasterId": 1442,
                        "ProjectAttributeMasterId": 6355,
                        "DispalyOrder": "3",
                        "DisplayAttributeName": "Non Core User",
                        "ControlName": "TextBox",
                        "AttributeName": "Non Core User"
                    },
                    "4": {
                        "AttributeMasterId": 1433,
                        "ProjectAttributeMasterId": 6336,
                        "DispalyOrder": "4",
                        "DisplayAttributeName": "Date",
                        "ControlName": "TextBox",
                        "AttributeName": "Date"
                    },
                    "5": {
                        "AttributeMasterId": 1384,
                        "ProjectAttributeMasterId": 6337,
                        "DispalyOrder": "5",
                        "DisplayAttributeName": "Tool URL",
                        "ControlName": "TextBox",
                        "AttributeName": "Tool URL"
                    },
                    "6": {
                        "AttributeMasterId": 1384,
                        "ProjectAttributeMasterId": 6337,
                        "DispalyOrder": "6",
                        "DisplayAttributeName": "Tool URL",
                        "ControlName": "TextBox",
                        "AttributeName": "Tool URL"
                    },
                    "7": {
                        "AttributeMasterId": 1385,
                        "ProjectAttributeMasterId": 6338,
                        "DispalyOrder": "7",
                        "DisplayAttributeName": "LISTING_NAME",
                        "ControlName": "TextBox",
                        "AttributeName": "LISTING_NAME"
                    },
                    "8": {
                        "AttributeMasterId": 1434,
                        "ProjectAttributeMasterId": 6340,
                        "DispalyOrder": "8",
                        "DisplayAttributeName": "Is the Website for the business?",
                        "ControlName": "DropDownList",
                        "AttributeName": "Is the Website for the business?"
                    },
                    "9": {
                        "AttributeMasterId": 1434,
                        "ProjectAttributeMasterId": 6340,
                        "DispalyOrder": "9",
                        "DisplayAttributeName": "Is the Website for the business?",
                        "ControlName": "DropDownList",
                        "AttributeName": "Is the Website for the business?"
                    },
                    "10": {
                        "AttributeMasterId": 267,
                        "ProjectAttributeMasterId": 6341,
                        "DispalyOrder": "10",
                        "DisplayAttributeName": "Reason",
                        "ControlName": "TextBox",
                        "AttributeName": "Reason"
                    },
                    "11": {
                        "AttributeMasterId": 263,
                        "ProjectAttributeMasterId": 6342,
                        "DispalyOrder": "11",
                        "DisplayAttributeName": "NOTES",
                        "ControlName": "TextBox",
                        "AttributeName": "NOTES"
                    },
                    "12": {
                        "AttributeMasterId": 1443,
                        "ProjectAttributeMasterId": 6356,
                        "DispalyOrder": "12",
                        "DisplayAttributeName": "Is it Closed?",
                        "ControlName": "DropDownList",
                        "AttributeName": "Is it Closed?"
                    },
                    "13": {
                        "AttributeMasterId": 1388,
                        "ProjectAttributeMasterId": 6357,
                        "DispalyOrder": "13",
                        "DisplayAttributeName": "Input Name",
                        "ControlName": "TextBox",
                        "AttributeName": "Input Name"
                    },
                    "14": {
                        "AttributeMasterId": 1436,
                        "ProjectAttributeMasterId": 6345,
                        "DispalyOrder": "14",
                        "DisplayAttributeName": "Source",
                        "ControlName": "TextBox",
                        "AttributeName": "Source"
                    },
                    "15": {
                        "AttributeMasterId": 1437,
                        "ProjectAttributeMasterId": 6346,
                        "DispalyOrder": "15",
                        "DisplayAttributeName": "Remarks",
                        "ControlName": "TextBox",
                        "AttributeName": "Remarks"
                    },
                    "17": {
                        "AttributeMasterId": 1396,
                        "ProjectAttributeMasterId": 6359,
                        "DispalyOrder": "17",
                        "DisplayAttributeName": "Input Phone",
                        "ControlName": "TextBox",
                        "AttributeName": "Input Phone"
                    },
                    "19": {
                        "AttributeMasterId": 1399,
                        "ProjectAttributeMasterId": 6360,
                        "DispalyOrder": "19",
                        "DisplayAttributeName": "Input_Phone numbers",
                        "ControlName": "TextBox",
                        "AttributeName": "Input_Phone numbers"
                    },
                    "20": {
                        "AttributeMasterId": 1427,
                        "ProjectAttributeMasterId": 6350,
                        "DispalyOrder": "20",
                        "DisplayAttributeName": "Hours of Operation",
                        "ControlName": "TextBox",
                        "AttributeName": "Hours of Operation"
                    },
                    "21": {
                        "AttributeMasterId": 1400,
                        "ProjectAttributeMasterId": 6361,
                        "DispalyOrder": "21",
                        "DisplayAttributeName": "Input_Phone Numbers Type",
                        "ControlName": "TextBox",
                        "AttributeName": "Input_Phone Numbers Type"
                    },
                    "24": {
                        "AttributeMasterId": 1405,
                        "ProjectAttributeMasterId": 6364,
                        "DispalyOrder": "24",
                        "DisplayAttributeName": "Input Website",
                        "ControlName": "TextBox",
                        "AttributeName": "Input Website"
                    },
                    "25": {
                        "AttributeMasterId": 1438,
                        "ProjectAttributeMasterId": 6351,
                        "DispalyOrder": "25",
                        "DisplayAttributeName": "Additional",
                        "ControlName": "TextBox",
                        "AttributeName": "Additional"
                    },
                    "26": {
                        "AttributeMasterId": 1409,
                        "ProjectAttributeMasterId": 6365,
                        "DispalyOrder": "26",
                        "DisplayAttributeName": "Input_Categories_Primary",
                        "ControlName": "TextBox",
                        "AttributeName": "Input_Categories_Primary"
                    },
                    "27": {
                        "AttributeMasterId": 1409,
                        "ProjectAttributeMasterId": 6365,
                        "DispalyOrder": "27",
                        "DisplayAttributeName": "Input_Categories_Primary",
                        "ControlName": "TextBox",
                        "AttributeName": "Input_Categories_Primary"
                    },
                    "28": {
                        "AttributeMasterId": 61,
                        "ProjectAttributeMasterId": 6375,
                        "DispalyOrder": "28",
                        "DisplayAttributeName": "Comments",
                        "ControlName": "MultiTextBox",
                        "AttributeName": "Comments"
                    },
                    "29": {
                        "AttributeMasterId": 1413,
                        "ProjectAttributeMasterId": 6367,
                        "DispalyOrder": "29",
                        "DisplayAttributeName": "Payment_Methods",
                        "ControlName": "TextBox",
                        "AttributeName": "Payment_Methods"
                    },
                    "31": {
                        "AttributeMasterId": 1446,
                        "ProjectAttributeMasterId": 6376,
                        "DispalyOrder": "31",
                        "DisplayAttributeName": "Batch",
                        "ControlName": "DropDownList",
                        "AttributeName": "Batch"
                    },
                    "33": {
                        "AttributeMasterId": 200,
                        "ProjectAttributeMasterId": 6377,
                        "DispalyOrder": "33",
                        "DisplayAttributeName": "Status",
                        "ControlName": "TextBox",
                        "AttributeName": "Status"
                    },
                    "34": {
                        "AttributeMasterId": 1447,
                        "ProjectAttributeMasterId": 6378,
                        "DispalyOrder": "34",
                        "DisplayAttributeName": "Input Category",
                        "ControlName": "DropDownList",
                        "AttributeName": "Input Category"
                    },
                    "36": {
                        "AttributeMasterId": 1444,
                        "ProjectAttributeMasterId": 6371,
                        "DispalyOrder": "36",
                        "DisplayAttributeName": "Services & Products",
                        "ControlName": "TextBox",
                        "AttributeName": "Services & Products"
                    },
                    "40": {
                        "AttributeMasterId": 1423,
                        "ProjectAttributeMasterId": 6373,
                        "DispalyOrder": "40",
                        "DisplayAttributeName": "Business Since",
                        "ControlName": "TextBox",
                        "AttributeName": "Business Since"
                    },
                    "41": {
                        "AttributeMasterId": 1424,
                        "ProjectAttributeMasterId": 6374,
                        "DispalyOrder": "41",
                        "DisplayAttributeName": "Since",
                        "ControlName": "TextBox",
                        "AttributeName": "Since"
                    }
                },
                "static": {
                    "1": {
                        "AttributeMasterId": 1383,
                        "ProjectAttributeMasterId": 6334,
                        "DispalyOrder": "1",
                        "DisplayAttributeName": "YPID",
                        "ControlName": "TextBox",
                        "AttributeName": "YPID"
                    },
                    "4": {
                        "AttributeMasterId": 1383,
                        "ProjectAttributeMasterId": 6334,
                        "DispalyOrder": "4",
                        "DisplayAttributeName": "YPID",
                        "ControlName": "TextBox",
                        "AttributeName": "YPID"
                    },
                    "5": {
                        "AttributeMasterId": 1383,
                        "ProjectAttributeMasterId": 6334,
                        "DispalyOrder": "5",
                        "DisplayAttributeName": "YPID",
                        "ControlName": "TextBox",
                        "AttributeName": "YPID"
                    },
                    "7": {
                        "AttributeMasterId": 225,
                        "ProjectAttributeMasterId": 6339,
                        "DispalyOrder": "7",
                        "DisplayAttributeName": "URL",
                        "ControlName": "TextBox",
                        "AttributeName": "URL"
                    },
                    "8": {
                        "AttributeMasterId": 225,
                        "ProjectAttributeMasterId": 6339,
                        "DispalyOrder": "8",
                        "DisplayAttributeName": "URL",
                        "ControlName": "TextBox",
                        "AttributeName": "URL"
                    }
                }
            },
            "1153": {
                "static": {
                    "1": {
                        "AttributeMasterId": 1383,
                        "ProjectAttributeMasterId": 6334,
                        "DispalyOrder": "1",
                        "DisplayAttributeName": "YPID",
                        "ControlName": "TextBox",
                        "AttributeName": "YPID"
                    },
                    "4": {
                        "AttributeMasterId": 1383,
                        "ProjectAttributeMasterId": 6334,
                        "DispalyOrder": "4",
                        "DisplayAttributeName": "YPID",
                        "ControlName": "TextBox",
                        "AttributeName": "YPID"
                    },
                    "5": {
                        "AttributeMasterId": 1383,
                        "ProjectAttributeMasterId": 6334,
                        "DispalyOrder": "5",
                        "DisplayAttributeName": "YPID",
                        "ControlName": "TextBox",
                        "AttributeName": "YPID"
                    }
                },
                "production": {
                    "12": {
                        "AttributeMasterId": 1389,
                        "ProjectAttributeMasterId": 6344,
                        "DispalyOrder": "12",
                        "DisplayAttributeName": "Mob_Name",
                        "ControlName": "TextBox",
                        "AttributeName": "Mob_Name"
                    },
                    "13": {
                        "AttributeMasterId": 1389,
                        "ProjectAttributeMasterId": 6344,
                        "DispalyOrder": "13",
                        "DisplayAttributeName": "Mob_Name",
                        "ControlName": "TextBox",
                        "AttributeName": "Mob_Name"
                    },
                    "14": {
                        "AttributeMasterId": 1389,
                        "ProjectAttributeMasterId": 6344,
                        "DispalyOrder": "14",
                        "DisplayAttributeName": "Mob_Name",
                        "ControlName": "TextBox",
                        "AttributeName": "Mob_Name"
                    }
                }
            },
            "1154": {
                "static": {
                    "1": {
                        "AttributeMasterId": 1383,
                        "ProjectAttributeMasterId": 6334,
                        "DispalyOrder": "1",
                        "DisplayAttributeName": "YPID",
                        "ControlName": "TextBox",
                        "AttributeName": "YPID"
                    },
                    "4": {
                        "AttributeMasterId": 1383,
                        "ProjectAttributeMasterId": 6334,
                        "DispalyOrder": "4",
                        "DisplayAttributeName": "YPID",
                        "ControlName": "TextBox",
                        "AttributeName": "YPID"
                    },
                    "5": {
                        "AttributeMasterId": 1383,
                        "ProjectAttributeMasterId": 6334,
                        "DispalyOrder": "5",
                        "DisplayAttributeName": "YPID",
                        "ControlName": "TextBox",
                        "AttributeName": "YPID"
                    }
                },
                "production": {
                    "16": {
                        "AttributeMasterId": 1393,
                        "ProjectAttributeMasterId": 6347,
                        "DispalyOrder": "16",
                        "DisplayAttributeName": "Mob_Address",
                        "ControlName": "TextBox",
                        "AttributeName": "Mob_Address"
                    }
                }
            }
        }
    },
    "Menu": {
        "1": {
            "Manage Project": {
                "Production Template Mapping": "ProductionFieldsMapping",
                "Output Template Mapping": "OutputMapping",
                "Prod Template": "ProductionFieldsMapping",
                "Project Configuration": "Projectconfig",
                "Module Configuration": "ModuleConfigs",
                "Job Definition": "UniqueIdFields",
                "Disposition definition": "DispositionRules",
                "Possible Values Configuration": "OptionMaster",
                "Validation Rule Engine": "Validationrules",
                "Autosuggest Configuration": "AutoSuggestion"
            }
        },
        "38": {
            "TestModule1": {
                "Production": "Getjobcore"
            }
        },
        "40": {
            "TestModule3": {
                "Production": "Getjobcore"
            }
        },
        "39": {
            "TestModule2": {
                "Production": "Getjobcore"
            }
        },
        "19": {
            "Manage Project": {
                "Production Template Mapping": "ProductionFieldsMapping",
                "Output Template Mapping": "OutputMapping",
                "Prod Template": "ProductionFieldsMapping",
                "Project Configuration": "Projectconfig",
                "Module Configuration": "ModuleConfigs",
                "Job Definition": "UniqueIdFields",
                "Disposition definition": "DispositionRules",
                "Possible Values Configuration": "OptionMaster",
                "Validation Rule Engine": "Validationrules",
                "Autosuggest Configuration": "AutoSuggestion"
            }
        },
        "41": {
            "Manage Project": {
                "Delivery Output": "DeliveryExport",
                "Input Import": "Importinitiates",
                "Production Dashboard": "ProductionDashBoards",
                "Production View": "ProductionView"
            },
            "Queries": {
                "PU Queries": "Puquery"
            }
        }
    },
    "ProjectStatus": {
        "1": "Testmodule3 Query Completed",
        "2": "Testmodule3 Query Inprogress",
        "3": "Testmodule3 Query",
        "4": "Testmodule3 Completed",
        "5": "Testmodule3 Inprogress",
        "6": "Ready for Testmodule3",
        "7": "Testmodule2 Query Completed",
        "8": "Testmodule2 Query Inprogress",
        "9": "Testmodule2 Query",
        "10": "Testmodule2 Completed",
        "11": "Testmodule2 Inprogress",
        "12": "Ready for Testmodule2",
        "13": "Testmodule1 Query Completed",
        "14": "Testmodule1 Query Inprogress",
        "15": "Testmodule1 Query",
        "16": "Testmodule1 Completed",
        "17": "Testmodule1 Inprogress",
        "18": "Ready for Testmodule1",
        "19": "Import Completed",
        "20": "Import Inprogress"
    },
    "Module": {
        "142": "Manage Project",
        "1152": "TestModule1",
        "1153": "TestModule2",
        "1154": "TestModule3",
        "141": "Queries"
    },
    "ModuleConfig": {
        "142": {
            "IsInputMandatory": 1,
            "IsHistoryTrack": 1,
            "IsUrlMonitoring": null,
            "IsAllowedToDisplay": null
        },
        "1152": {
            "IsInputMandatory": 1,
            "IsHistoryTrack": 1,
            "IsUrlMonitoring": 0,
            "IsAllowedToDisplay": 0
        },
        "1153": {
            "IsInputMandatory": 2,
            "IsHistoryTrack": 2,
            "IsUrlMonitoring": null,
            "IsAllowedToDisplay": null
        },
        "1154": {
            "IsInputMandatory": 2,
            "IsHistoryTrack": 2,
            "IsUrlMonitoring": null,
            "IsAllowedToDisplay": null
        }
    },
    "ModuleUser": {
        "142": {
            "100553": {
                "Id": 100553,
                "Username": "Administrator"
            },
            "102131": {
                "Id": 102131,
                "Username": "twopointzero"
            },
            "102229": {
                "Id": 102229,
                "Username": "TestLead"
            }
        },
        "1152": {
            "95534": {
                "Id": 95534,
                "Username": "usertwo"
            },
            "95543": {
                "Id": 95543,
                "Username": "userthree"
            }
        },
        "1153": {
            "95548": {
                "Id": 95548,
                "Username": "userfour"
            },
            "95553": {
                "Id": 95553,
                "Username": "userfive"
            }
        },
        "1154": {
            "95558": {
                "Id": 95558,
                "Username": "usersix"
            },
            "95563": {
                "Id": 95563,
                "Username": "userseven"
            }
        },
        "141": {
            "102229": {
                "Id": 102229,
                "Username": "TestLead"
            }
        }
    },
    "ModuleStatusList": {
        "1152": [
            "Ready for Testmodule1",
            "Testmodule1 Inprogress",
            "Testmodule1 Completed",
            "Testmodule1 Query",
            "Testmodule1 Query Inprogress",
            "Testmodule1 Query Completed"
        ],
        "1153": [
            "Ready for Testmodule2",
            "Testmodule2 Inprogress",
            "Testmodule2 Completed",
            "Testmodule2 Query",
            "Testmodule2 Query Inprogress",
            "Testmodule2 Query Completed",
            "Noncore Rework",
            "Noncore Rework InProgress"
        ],
        "1154": [
            "Ready for HOO Production",
            "HOO Production InProgress",
            "HOO Production Completed",
            "HOO Query",
            "HOO Query InProgress",
            "HOO Query Completed"
        ]
    },
    "ModuleStatus": {
        "1152": {
            "19": {
                "ModuleId": 1152,
                "ModStatus": "Ready for Testmodule1",
                "ModuleStatusIdentifier": "ReadyforCoreProduction",
                "StatusId": 19,
                "FromStatus": "Import Completed"
            },
            "18": {
                "ModuleId": 1152,
                "ModStatus": "Testmodule1 Inprogress",
                "ModuleStatusIdentifier": "CoreProductionInProgress",
                "StatusId": 18,
                "FromStatus": "Ready for Testmodule1"
            },
            "17": {
                "ModuleId": 1152,
                "ModStatus": "Testmodule1 Query",
                "ModuleStatusIdentifier": "CoreQuery",
                "StatusId": 17,
                "FromStatus": "Testmodule1 Inprogress"
            },
            "15": {
                "ModuleId": 1152,
                "ModStatus": "Testmodule1 Query Completed",
                "ModuleStatusIdentifier": "CoreQueryCompleted",
                "StatusId": 15,
                "FromStatus": "Testmodule1 Query"
            },
            "14": {
                "ModuleId": 1152,
                "ModStatus": "Testmodule1 Query Inprogress",
                "ModuleStatusIdentifier": "CoreQueryInProgress",
                "StatusId": 14,
                "FromStatus": "Testmodule1 Query Inprogress"
            }
        },
        "1153": {
            "16": {
                "ModuleId": 1153,
                "ModStatus": "Ready for Testmodule2",
                "ModuleStatusIdentifier": "ReadyforNonCoreProduction",
                "StatusId": 16,
                "FromStatus": "Testmodule1 Completed"
            },
            "12": {
                "ModuleId": 1153,
                "ModStatus": "Testmodule2 Inprogress",
                "ModuleStatusIdentifier": "NonCoreProductionInProgress",
                "StatusId": 12,
                "FromStatus": "Ready for Testmodule2"
            },
            "11": {
                "ModuleId": 1153,
                "ModStatus": "Testmodule2 Query",
                "ModuleStatusIdentifier": "NonCoreQuery",
                "StatusId": 11,
                "FromStatus": "Testmodule2 Inprogress"
            },
            "9": {
                "ModuleId": 1153,
                "ModStatus": "Testmodule2 Query Completed",
                "ModuleStatusIdentifier": "NonCoreQueryCompleted",
                "StatusId": 9,
                "FromStatus": "Testmodule2 Query"
            },
            "8": {
                "ModuleId": 1153,
                "ModStatus": "Testmodule2 Query Inprogress",
                "ModuleStatusIdentifier": "NonCoreQueryInProgress",
                "StatusId": 8,
                "FromStatus": "Testmodule2 Query Inprogress"
            }
        },
        "1154": {
            "10": {
                "ModuleId": 1154,
                "ModStatus": "Ready for HOO Production",
                "ModuleStatusIdentifier": "ReadyforHOOProduction",
                "StatusId": 10,
                "FromStatus": "Testmodule2 Completed"
            },
            "6": {
                "ModuleId": 1154,
                "ModStatus": "HOO Production InProgress",
                "ModuleStatusIdentifier": "HOOProductionInProgress",
                "StatusId": 6,
                "FromStatus": "Ready for Testmodule3"
            },
            "5": {
                "ModuleId": 1154,
                "ModStatus": "HOO Query",
                "ModuleStatusIdentifier": "HOOQuery",
                "StatusId": 5,
                "FromStatus": "Testmodule3 Inprogress"
            },
            "3": {
                "ModuleId": 1154,
                "ModStatus": "HOO Query Completed",
                "ModuleStatusIdentifier": "HOOQueryCompleted",
                "StatusId": 3,
                "FromStatus": "Testmodule3 Query"
            },
            "2": {
                "ModuleId": 1154,
                "ModStatus": "HOO Query InProgress",
                "ModuleStatusIdentifier": "HOOQueryInProgress",
                "StatusId": 2,
                "FromStatus": "Testmodule3 Query Inprogress"
            }
        }
    },
    "ModuleStatus_Navigation": {
        "19": [
            "Ready for Testmodule1",
            18
        ],
        "18": [
            "Testmodule1 Inprogress",
            17
        ],
        "17": [
            "Testmodule1 Completed",
            16,
            [
                "Testmodule1 Query",
                15
            ]
        ],
        "15": [
            "Testmodule1 Query Completed",
            13
        ],
        "14": [
            "Testmodule1 Query Inprogress",
            14
        ],
        "16": [
            "Ready for Testmodule2",
            12
        ],
        "12": [
            "Testmodule2 Inprogress",
            11
        ],
        "11": [
            "Testmodule2 Completed",
            10,
            [
                "Testmodule2 Query",
                9
            ]
        ],
        "9": [
            "Testmodule2 Query Completed",
            7
        ],
        "8": [
            "Testmodule2 Query Inprogress",
            8
        ],
        "10": [
            "Ready for HOO Production",
            false
        ],
        "6": [
            "HOO Production InProgress",
            false
        ],
        "5": [
            "HOO Production Completed",
            false,
            [
                "HOO Query",
                false
            ]
        ],
        "3": [
            "HOO Query Completed",
            false
        ],
        "2": [
            "HOO Query InProgress",
            false
        ]
    },
    "ProjectConfig": {
        "DomainId": "1383",
        "DomainUrl": "225",
        "ProdDB_PageLimit": "50",
        "ProductionView": "1"
    }
}